django_drf_utils/__init__.py
django_drf_utils/config.py
django_drf_utils/email.py
django_drf_utils/exception_handler.py
django_drf_utils/exceptions.py
django_drf_utils/logging_utils.py
django_drf_utils/models.py
django_drf_utils/permissions.py
django_drf_utils/py.typed
django_drf_utils/serializers/__init__.py
django_drf_utils/serializers/fields.py
django_drf_utils/serializers/utils.py
django_drf_utils/serializers/validators.py
django_drf_utils/tests/__init__.py
django_drf_utils/tests/factories.py
django_drf_utils/tests/utils.py
django_drf_utils/tests/models/__init__.py
django_drf_utils/tests/models/utils.py
django_drf_utils/views/__init__.py
django_drf_utils/views/log.py
django_drf_utils/views/utils.py
django_drf_utils-2.14.2.dist-info/METADATA
django_drf_utils-2.14.2.dist-info/WHEEL
django_drf_utils-2.14.2.dist-info/licenses/LICENSE
django_drf_utils-2.14.2.dist-info/RECORD
